MANIFEST.in
changelog.rst
readme.rst
setup.py
LaunchyTomboyPlugin.egg-info/PKG-INFO
LaunchyTomboyPlugin.egg-info/SOURCES.txt
LaunchyTomboyPlugin.egg-info/dependency_links.txt
LaunchyTomboyPlugin.egg-info/not-zip-safe
LaunchyTomboyPlugin.egg-info/top_level.txt
launchytomboyplugin/__init__.py
launchytomboyplugin/lib.py
launchytomboyplugin/icons/notebook-new.png
launchytomboyplugin/icons/tomboy.png