Metadata-Version: 1.0
Name: LaunchyTomboyPlugin
Version: 0.1.1
Summary: A plugin for Launchy to put Tomboy note titles in the catalog
Home-page: http://bitbucket.org/rsyring/launchytomboyplugin
Author: Randy Syring
Author-email: rsyring@gmail.com
License: BSD
Platform: UNKNOWN
Classifier: Development Status :: 4 - Beta
Classifier: Intended Audience :: End Users/Desktop
Classifier: License :: OSI Approved :: BSD License
Classifier: Operating System :: Microsoft :: Windows
Classifier: Programming Language :: Python :: 2.7
